README.txt
setup.py
collective/__init__.py
collective.perseoschema.egg-info/PKG-INFO
collective.perseoschema.egg-info/SOURCES.txt
collective.perseoschema.egg-info/dependency_links.txt
collective.perseoschema.egg-info/entry_points.txt
collective.perseoschema.egg-info/namespace_packages.txt
collective.perseoschema.egg-info/not-zip-safe
collective.perseoschema.egg-info/paster_plugins.txt
collective.perseoschema.egg-info/requires.txt
collective.perseoschema.egg-info/top_level.txt
collective/perseoschema/__init__.py
collective/perseoschema/configure.zcml
collective/perseoschema/skins.zcml
collective/perseoschema/tests.py
collective/perseoschema/Extensions/install.py
collective/perseoschema/browser/__init__.py
collective/perseoschema/browser/configure.zcml
collective/perseoschema/browser/interfaces.py
collective/perseoschema/browser/seo_config.py
collective/perseoschema/browser/views.py
collective/perseoschema/browser/templates/path_bar.pt
collective/perseoschema/browser/templates/perseo_tab_context.pt
collective/perseoschema/browser/templates/portal_header.pt
collective/perseoschema/browser/templates/sections.pt
collective/perseoschema/profiles/default/browserlayer.xml
collective/perseoschema/profiles/default/metadata.xml
collective/perseoschema/profiles/default/skins.xml
collective/perseoschema/profiles/uninstall/skins.xml
collective/perseoschema/skins/collective.perseo.schema.org/main_template.pt
docs/HISTORY.txt
docs/INSTALL.txt
docs/LICENSE.GPL
docs/LICENSE.txt