Metadata-Version: 1.0
Name: collective.perseoschema
Version: 0.1.1
Summary: Adds Schema.org attributes to collective.perseo package
Home-page: http://svn.plone.org/svn/collective/
Author: RedTurtle Technology
Author-email: sviluppoplone@redturtle.net
License: GPL
Platform: UNKNOWN
Classifier: Framework :: Plone
Classifier: Programming Language :: Python
